neo4j_aura_sdk/__init__.py
neo4j_aura_sdk/client.py
neo4j_aura_sdk/models.py
neo4j_aura_sdk-0.1.2.dist-info/METADATA
neo4j_aura_sdk-0.1.2.dist-info/WHEEL
neo4j_aura_sdk-0.1.2.dist-info/RECORD
