Metadata-Version: 2.3
Name: neo4j-aura-sdk
Version: 0.1.2
Summary: 
Author: Zach Probst
Author-email: Zach_Probst@intuit.com
Requires-Python: >=3.10,<4.0
Classifier: Programming Language :: Python :: 3
Classifier: Programming Language :: Python :: 3.10
Classifier: Programming Language :: Python :: 3.11
Classifier: Programming Language :: Python :: 3.12
Classifier: Programming Language :: Python :: 3.13
Requires-Dist: httpx (>=0.27.0,<0.28.0)
Requires-Dist: pydantic (>=2.7.3,<3.0.0)
